[
  {
    "name": "5P",
    "picture": "https://dustloop.com/wiki/images/thumb/7/71/GGST_Potemkin_5P.png/210px-GGST_Potemkin_5P.png",
    "input": "5P",
    "damage": 30,
    "guard": "All",
    "startup": 5,
    "active": 5,
    "recovery": 6,
    "onBlock": 1,
    "onHit": 4,
    "riscGain": 1000,
    "riscLoss": 1500,
    "level": 1,
    "counter": "Small",
    "invul": "",
    "prorate": "80%"
  },
  {
    "name": "5K",
    "picture": "https://dustloop.com/wiki/images/thumb/b/b2/GGST_Potemkin_5K.png/210px-GGST_Potemkin_5K.png",
    "input": "5K",
    "damage": 36,
    "guard": "Low",
    "startup": 10,
    "active": 9,
    "recovery": 9,
    "onBlock": -4,
    "onHit": -1,
    "riscGain": 1125,
    "riscLoss": 1000,
    "level": 2,
    "counter": "Small",
    "invul": "",
    "prorate": "70%"
  },
  {
    "name": "c.S",
    "picture": "https://dustloop.com/wiki/images/thumb/5/53/GGST_Potemkin_c.S.png/210px-GGST_Potemkin_c.S.png",
    "input": "c.S",
    "damage": 45,
    "guard": "All",
    "startup": 8,
    "active": 4,
    "recovery": 11,
    "onBlock": 4,
    "onHit": 7,
    "riscGain": 2500,
    "riscLoss": 1000,
    "level": 4,
    "counter": "Mid",
    "invul": "",
    "prorate": "100%"
  },
  {
    "name": "f.S",
    "picture": "https://dustloop.com/wiki/images/thumb/6/61/GGST_Potemkin_f.S.png/210px-GGST_Potemkin_f.S.png",
    "input": "f.S",
    "damage": 40,
    "guard": "All",
    "startup": 12,
    "active": 7,
    "recovery": 18,
    "onBlock": -8,
    "onHit": -5,
    "riscGain": 2000,
    "riscLoss": 1000,
    "level": 3,
    "counter": "Mid",
    "invul": "",
    "prorate": "90%"
  },
  {
    "name": "5H",
    "picture": "https://dustloop.com/wiki/images/thumb/6/61/GGST_Potemkin_f.S.png/210px-GGST_Potemkin_f.S.png",
    "input": "5H",
    "damage": 60,
    "guard": "All",
    "startup": 16,
    "active": 5,
    "recovery": 25,
    "onBlock": -11,
    "onHit": -8,
    "riscGain": 2500,
    "riscLoss": 1000,
    "level": 4,
    "counter": "Large",
    "invul": "",
    "prorate": "100%"
  },
  {
    "name": "5D",
    "picture": "https://dustloop.com/wiki/images/thumb/d/d3/GGST_Potemkin_5D.png/210px-GGST_Potemkin_5D.png",
    "input": "5D",
    "damage": 50,
    "guard": "High",
    "startup": "20~27",
    "active": 8,
    "recovery": 21,
    "onBlock": -15,
    "onHit": 0,
    "riscGain": 1125,
    "riscLoss": 3000,
    "level": 2,
    "counter": "Mid",
    "invul": "",
    "prorate": "80%"
  },
  {
    "name": "5[D]",
    "picture": "https://dustloop.com/wiki/images/thumb/d/d3/GGST_Potemkin_5D.png/210px-GGST_Potemkin_5D.png",
    "input": "5[D]",
    "damage": 62,
    "guard": "High",
    "startup": 28,
    "active": 8,
    "recovery": 21,
    "onBlock": -10,
    "onHit": "SKD +38",
    "riscGain": 1875,
    "riscLoss": 1500,
    "level": 4,
    "counter": "Mid",
    "invul": "",
    "prorate": "100%"
  },
  {
    "name": "2P",
    "picture": "https://dustloop.com/wiki/images/thumb/8/8b/GGST_Potemkin_2P.png/210px-GGST_Potemkin_2P.png",
    "input": "2P",
    "damage": 26,
    "guard": "All",
    "startup": 8,
    "active": 4,
    "recovery": 9,
    "onBlock": -1,
    "onHit": 2,
    "riscGain": 1000,
    "riscLoss": 1500,
    "level": 1,
    "counter": "Small",
    "invul": "",
    "prorate": "80%"
  },
  {
    "name": "2K",
    "picture": "https://dustloop.com/wiki/images/thumb/a/a5/GGST_Potemkin_2K.png/210px-GGST_Potemkin_2K.png",
    "input": "2K",
    "damage": 30,
    "guard": "Low",
    "startup": 10,
    "active": 4,
    "recovery": 14,
    "onBlock": -4,
    "onHit": -1,
    "riscGain": 1125,
    "riscLoss": 1000,
    "level": 2,
    "counter": "Small",
    "invul": "",
    "prorate": "70%"
  },
  {
    "name": "2S",
    "picture": "https://dustloop.com/wiki/images/thumb/6/6b/GGST_Potemkin_2S.png/210px-GGST_Potemkin_2S.png",
    "input": "2S",
    "damage": 45,
    "guard": "All",
    "startup": 14,
    "active": 3,
    "recovery": 18,
    "onBlock": -4,
    "onHit": -1,
    "riscGain": 2000,
    "riscLoss": 1000,
    "level": 3,
    "counter": "Mid",
    "invul": "",
    "prorate": "90%"
  },
  {
    "name": "2H",
    "picture": "https://dustloop.com/wiki/images/thumb/8/87/GGST_Potemkin_2H.png/156px-GGST_Potemkin_2H.png",
    "input": "2H",
    "damage": 55,
    "guard": "All",
    "startup": 13,
    "active": 5,
    "recovery": 35,
    "onBlock": -21,
    "onHit": "SKD (+27)",
    "riscGain": 2500,
    "riscLoss": 1000,
    "level": 4,
    "counter": "Large",
    "invul": "",
    "prorate": "100%"
  },
  {
    "name": "2D",
    "picture": "https://dustloop.com/wiki/images/thumb/9/99/GGST_Potemkin_2D.png/210px-GGST_Potemkin_2D.png",
    "input": "2D",
    "damage": 40,
    "guard": "Low",
    "startup": 13,
    "active": 7,
    "recovery": 21,
    "onBlock": -11,
    "onHit": "KD",
    "riscGain": 1500,
    "riscLoss": 1000,
    "level": 3,
    "counter": "Large",
    "invul": "",
    "prorate": "90%"
  },
  {
    "name": "6P",
    "picture": "https://dustloop.com/wiki/images/thumb/e/e0/GGST_Potemkin_6P.png/183px-GGST_Potemkin_6P.png",
    "input": "6P",
    "damage": 42,
    "guard": "All",
    "startup": 11,
    "active": 7,
    "recovery": 25,
    "onBlock": -15,
    "onHit": "SKD (+29)",
    "riscGain": 2000,
    "riscLoss": 1000,
    "level": 3,
    "counter": "Mid",
    "invul": "1 ~ 4F Upper Body\n5 ~ 17F Above Knees",
    "prorate": "90%"
  },
  {
    "name": "6K",
    "picture": "https://dustloop.com/wiki/images/thumb/3/35/GGST_Potemkin_6K.png/210px-GGST_Potemkin_6K.png",
    "input": "6K",
    "damage": 45,
    "guard": "All",
    "startup": 22,
    "active": 5,
    "recovery": 18,
    "onBlock": -6,
    "onHit": -3,
    "riscGain": 2000,
    "riscLoss": 1000,
    "level": 3,
    "counter": "Mid",
    "invul": "",
    "prorate": "100%"
  },
  {
    "name": "6H",
    "picture": "https://dustloop.com/wiki/images/thumb/a/a3/GGST_Potemkin_6H.png/210px-GGST_Potemkin_6H.png",
    "input": "6H",
    "damage": 90,
    "guard": "All",
    "startup": 23,
    "active": 5,
    "recovery": 29,
    "onBlock": -15,
    "onHit": "SKD (+25)",
    "riscGain": 2500,
    "riscLoss": 1000,
    "level": 4,
    "counter": "Large",
    "invul": "",
    "prorate": "100%"
  },
  {
    "name": "j.P",
    "picture": "https://dustloop.com/wiki/images/thumb/e/e5/GGST_Potemkin_j.P.png/210px-GGST_Potemkin_j.P.png",
    "input": "j.P",
    "damage": 30,
    "guard": "High",
    "startup": 7,
    "active": 6,
    "recovery": 6,
    "onBlock": "",
    "onHit": "",
    "riscGain": 375,
    "riscLoss": 1000,
    "level": 0,
    "counter": "Small",
    "invul": "",
    "prorate": "80%"
  },
  {
    "name": "j.K",
    "picture": "https://dustloop.com/wiki/images/thumb/4/45/GGST_Potemkin_j.K.png/210px-GGST_Potemkin_j.K.png",
    "input": "j.K",
    "damage": 36,
    "guard": "High",
    "startup": 10,
    "active": 6,
    "recovery": 15,
    "onBlock": "",
    "onHit": "",
    "riscGain": 750,
    "riscLoss": 1000,
    "level": 1,
    "counter": "Small",
    "invul": "",
    "prorate": "80%"
  },
  {
    "name": "j.S",
    "picture": "https://dustloop.com/wiki/images/thumb/c/cf/GGST_Potemkin_j.S.png/156px-GGST_Potemkin_j.S.png",
    "input": "j.S",
    "damage": 45,
    "guard": "High",
    "startup": 13,
    "active": 5,
    "recovery": 23,
    "onBlock": "",
    "onHit": "",
    "riscGain": 1500,
    "riscLoss": 1000,
    "level": 3,
    "counter": "Mid",
    "invul": "",
    "prorate": "80%"
  },
  {
    "name": "j.H",
    "picture": "https://dustloop.com/wiki/images/thumb/1/14/GGST_Potemkin_j.H.png/210px-GGST_Potemkin_j.H.png",
    "input": "j.H",
    "damage": 55,
    "guard": "High",
    "startup": 12,
    "active": 4,
    "recovery": 16,
    "onBlock": "",
    "onHit": "",
    "riscGain": 1875,
    "riscLoss": 1000,
    "level": 4,
    "counter": "Mid",
    "invul": "",
    "prorate": "80%"
  },
  {
    "name": "j.D",
    "picture": "https://dustloop.com/wiki/images/thumb/f/f3/GGST_Potemkin_j.D.png/210px-GGST_Potemkin_j.D.png",
    "input": "j.D",
    "damage": 50,
    "guard": "All",
    "startup": 13,
    "active": "Until Landing",
    "recovery": "9 After landing",
    "onBlock": "",
    "onHit": "",
    "riscGain": 2000,
    "riscLoss": 1000,
    "level": 3,
    "counter": "Mid",
    "invul": "",
    "prorate": "80%"
  },
  {
    "name": "Hammer Fall",
    "picture": "https://dustloop.com/wiki/images/thumb/3/37/GGST_Potemkin_Hammer_Fall.png/210px-GGST_Potemkin_Hammer_Fall.png",
    "input": "[4]6H",
    "damage": 58,
    "guard": "All",
    "startup": "18~62",
    "active": "2f",
    "recovery": 26,
    "onBlock": -9,
    "onHit": "SKD (+22)",
    "riscGain": 2500,
    "riscLoss": 1000,
    "level": "",
    "counter": "Mid",
    "invul": "",
    "prorate": "80%"
  },
  {
    "name": "Hammer Fall Break",
    "picture": "https://dustloop.com/wiki/images/thumb/9/9e/GGST_Potemkin_Air_Throw.png/210px-GGST_Potemkin_Air_Throw.png",
    "input": "[4]6H P",
    "damage": "N/A",
    "guard": "N/A",
    "startup": "",
    "active": "",
    "recovery": 27,
    "onBlock": "",
    "onHit": "",
    "riscGain": "",
    "riscLoss": "",
    "level": "",
    "counter": "",
    "invul": "",
    "prorate": ""
  },
  {
    "name": "Potemkin Buster",
    "picture": "https://dustloop.com/wiki/images/thumb/a/ab/GGST_Potemkin_Potemkin_Buster.png/210px-GGST_Potemkin_Potemkin_Buster.png",
    "input": "632146P",
    "damage": 175,
    "guard": "Ground Throw",
    "startup": 5,
    "active": 4,
    "recovery": 37,
    "onBlock": "",
    "onHit": "",
    "riscGain": "",
    "riscLoss": 2500,
    "level": "",
    "counter": "",
    "invul": "1 ~ 8F Throw",
    "prorate": "50%"
  },
  {
    "name": "Heat Knuckle",
    "picture": "https://dustloop.com/wiki/images/thumb/d/d0/GGST_Potemkin_Heat_Knuckle_1.png/206px-GGST_Potemkin_Heat_Knuckle_1.png",
    "input": "623H",
    "damage": "0.8×7.60",
    "guard": "Air Guard Crush",
    "startup": 12,
    "active": 4,
    "recovery": 18,
    "onBlock": "+10~+1",
    "onHit": "KD/Wall Break",
    "riscGain": 3750,
    "riscLoss": 2500,
    "level": "",
    "counter": "Very Small",
    "invul": "",
    "prorate": "50%"
  },
  {
    "name": "Mega Fist",
    "picture": "https://dustloop.com/wiki/images/thumb/9/9e/GGST_Potemkin_Mega_Fist.png/197px-GGST_Potemkin_Mega_Fist.png",
    "input": "236P",
    "damage": 50,
    "guard": "High",
    "startup": 25,
    "active": 7,
    "recovery": 16,
    "onBlock": -6,
    "onHit": -2,
    "riscGain": 1500,
    "riscLoss": 1000,
    "level": 3,
    "counter": "Mid",
    "invul": "",
    "prorate": "80%"
  },
  {
    "name": "Back Mega Fist",
    "picture": "https://dustloop.com/wiki/images/thumb/9/9e/GGST_Potemkin_Mega_Fist.png/197px-GGST_Potemkin_Mega_Fist.png",
    "input": "214P",
    "damage": 50,
    "guard": "High",
    "startup": 25,
    "active": 7,
    "recovery": 6,
    "onBlock": 4,
    "onHit": 8,
    "riscGain": 1500,
    "riscLoss": 1000,
    "level": 3,
    "counter": "Mid",
    "invul": "",
    "prorate": "80%"
  },
  {
    "name": "Kara Mega Fist",
    "picture": "https://dustloop.com/wiki/images/thumb/9/9e/GGST_Potemkin_Mega_Fist.png/197px-GGST_Potemkin_Mega_Fist.png",
    "input": "2146K~P",
    "damage": 80,
    "guard": "High",
    "startup": "26-27",
    "active": 7,
    "recovery": 12,
    "onBlock": -2,
    "onHit": 2,
    "riscGain": 1500,
    "riscLoss": 1000,
    "level": 3,
    "counter": "Mid",
    "invul": "",
    "prorate": "80%"
  },
  {
    "name": "Slide Head",
    "picture": "https://dustloop.com/wiki/images/thumb/9/90/GGST_Potemkin_Slide_Head.png/210px-GGST_Potemkin_Slide_Head.png",
    "input": "236S",
    "damage": 0,
    "guard": "Low (Guard Crush)",
    "startup": 29,
    "active": 2,
    "recovery": 28,
    "onBlock": 0,
    "onHit": "KD",
    "riscGain": 375,
    "riscLoss": 1000,
    "level": 4,
    "counter": "Very Small",
    "invul": "",
    "prorate": "80%"
  },
  {
    "name": "F.D.B.",
    "picture": "https://dustloop.com/wiki/images/thumb/c/cf/GGST_Potemkin_FDB.png/210px-GGST_Potemkin_FDB.png",
    "input": "63214S",
    "damage": "55 [75]",
    "guard": "All",
    "startup": "21~38 [38]",
    "active": 3,
    "recovery": 20,
    "onBlock": -6,
    "onHit": "KD",
    "riscGain": 2000,
    "riscLoss": 1000,
    "level": 3,
    "counter": "Mid",
    "invul": "4 ~ [20~37F] Reflect",
    "prorate": "100%"
  },
  {
    "name": "Reflect Projectile",
    "picture": "https://dustloop.com/wiki/images/thumb/f/f2/GGST_Potemkin_FDB_Reflect.png/210px-GGST_Potemkin_FDB_Reflect.png",
    "input": "Reflect Projectile",
    "damage": 50,
    "guard": "All",
    "startup": 1,
    "active": "",
    "recovery": "",
    "onBlock": 11,
    "onHit": "SKD (+46)",
    "riscGain": 500,
    "riscLoss": 1000,
    "level": 3,
    "counter": "Very Small",
    "invul": "",
    "prorate": "80%"
  },
  {
    "name": "Garuda Impact",
    "picture": "https://dustloop.com/wiki/images/thumb/1/1b/GGST_Potemkin_Garuda_Impact.png/210px-GGST_Potemkin_Garuda_Impact.png",
    "input": "214H",
    "damage": 63,
    "guard": "All (Guard Crush)",
    "startup": 28,
    "active": 11,
    "recovery": 24,
    "onBlock": 19,
    "onHit": "+17~+35",
    "riscGain": 2500,
    "riscLoss": 2000,
    "level": "",
    "counter": "Large",
    "invul": "",
    "prorate": "100%"
  }
]